edr_agent_validator/__init__.py
edr_agent_validator/activity.py
edr_agent_validator/console.py
edr_agent_validator/files.py
edr_agent_validator/network.py
edr_agent_validator/process.py
edr_agent_validator-0.2.0.dist-info/entry_points.txt
edr_agent_validator-0.2.0.dist-info/WHEEL
edr_agent_validator-0.2.0.dist-info/METADATA
edr_agent_validator-0.2.0.dist-info/RECORD
