Metadata-Version: 2.1
Name: edr-agent-validator
Version: 0.2.0
Summary: The Red Canary EDR validation tool.
Home-page: https://github.com/andrew-kennedy/edr-agent-validator
Author: Andrew Kennedy
Author-email: andrewk36@gmail.com
Requires-Python: >=3.10,<4.0
Classifier: Programming Language :: Python :: 3
Classifier: Programming Language :: Python :: 3.10
Requires-Dist: desert (>=2020.11.18,<2021.0.0)
Requires-Dist: marshmallow (>=3.14.1,<4.0.0)
Requires-Dist: marshmallow-enum (>=1.5.1,<2.0.0)
Requires-Dist: psutil (>=5.9.0,<6.0.0)
Requires-Dist: typer (>=0.4.0,<0.5.0)
